scraper/__init__.py
scraper/twitter_scraper.py
twitter_cli_scraper-0.1.2.dist-info/LICENSE
twitter_cli_scraper-0.1.2.dist-info/METADATA
twitter_cli_scraper-0.1.2.dist-info/WHEEL
twitter_cli_scraper-0.1.2.dist-info/entry_points.txt
twitter_cli_scraper-0.1.2.dist-info/top_level.txt
twitter_cli_scraper-0.1.2.dist-info/RECORD
