Metadata-Version: 2.1
Name: twitter-cli-scraper
Version: 0.1.2
Summary: A CLI tool for scraping Twitter trends and tweets.
Home-page: https://github.com/bsse23087/twitter-cli-scraper
Author: Muhammad Abdullah
Author-email: muhammadabdullah07014@gmail.com
License: UNKNOWN
Platform: UNKNOWN
Classifier: Programming Language :: Python :: 3
Classifier: License :: OSI Approved :: MIT License
Classifier: Operating System :: OS Independent
Requires-Python: >=3.6
License-File: LICENSE
Requires-Dist: pandas
Requires-Dist: selenium
Requires-Dist: webdriver-manager
